br_lottery_simulation/__init__.py
br_lottery_simulation/play/__init__.py
br_lottery_simulation/play/prize_draw.py
br_lottery_simulation/play/utils.py
br_lottery_simulation-0.0.10.dist-info/LICENSE
br_lottery_simulation-0.0.10.dist-info/METADATA
br_lottery_simulation-0.0.10.dist-info/WHEEL
br_lottery_simulation-0.0.10.dist-info/top_level.txt
br_lottery_simulation-0.0.10.dist-info/RECORD
