Metadata-Version: 2.1
Name: br-lottery-simulation
Version: 0.0.10
Summary: brazilian lottery game simulation
Home-page: https://github.com/rd-oliveira/br-lottery-simulation
Author: richard_oliveira
Author-email: doomsdayst9@gmail.com
Requires-Python: >=3.10
License-File: LICENSE
